broadcastio/__init__.py
broadcastio/core/attachment.py
broadcastio/core/error_codes.py
broadcastio/core/exceptions.py
broadcastio/core/health.py
broadcastio/core/message.py
broadcastio/core/orchestrator.py
broadcastio/core/result.py
broadcastio/providers/base.py
broadcastio/providers/dummy.py
broadcastio/providers/telegram.py
broadcastio/providers/whatsapp.py
broadcastio-0.2.1.dist-info/licenses/LICENSE
tests/test_message_metadata.py
tests/test_orchestrator_provider_errors.py
tests/test_orchestrator_validation.py
broadcastio-0.2.1.dist-info/METADATA
broadcastio-0.2.1.dist-info/WHEEL
broadcastio-0.2.1.dist-info/top_level.txt
broadcastio-0.2.1.dist-info/RECORD
