Metadata-Version: 2.4
Name: broadcastio
Version: 0.2.1
Summary: Provider-agnostic message broadcasting with fallback orchestration
Author: Naufal Hilmiaji
Maintainer: Naufal Hilmiaji
License: MIT License
Project-URL: Homepage, https://github.com/naufalhilmiaji/broadcastio
Project-URL: Repository, https://github.com/naufalhilmiaji/broadcastio
Project-URL: Issues, https://github.com/naufalhilmiaji/broadcastio/issues
Keywords: messaging,notifications,orchestration,fallback,whatsapp
Classifier: Development Status :: 3 - Alpha
Classifier: Programming Language :: Python :: 3
Classifier: Programming Language :: Python :: 3.10
Classifier: Programming Language :: Python :: 3.11
Classifier: Programming Language :: Python :: 3.12
Classifier: License :: OSI Approved :: MIT License
Classifier: Operating System :: OS Independent
Requires-Python: >=3.10
License-File: LICENSE
Requires-Dist: requests>=2.31
Dynamic: license-file
